<METurn METURNVERSION="V2.0.2"><TurnInfo><GameNo>141</GameNo><TurnNo>25</TurnNo><NationNo>22</NationNo><GameType>Fourth Age, circa 1000</GameType><NationCapitalHex>4112</NationCapitalHex><DueDate>SEPTEMBER 22 2013</DueDate><Secret>7309</Secret><Player>EUGENIO RUGGERIO</Player><Account>109721</Account><NationEliminated>0</NationEliminated><Int>9E69946C669B996895636D9D9967</Int></TurnInfo><Characters><Character ID="cener"><Name>Cenerentola</Name><Location>1219</Location><Nation>0</Nation><Command>0</Command><TotalCommand>0</TotalCommand><Agent>0</Agent><TotalAgent>0</TotalAgent><Emmisary>0</Emmisary><TotalEmmisary>0</TotalEmmisary><Mage>0</Mage><TotalMage>0</TotalMage><Stealth>0</Stealth><TotalStealth>0</TotalStealth><Challenge>0</Challenge><Health>0</Health><Title></Title><InformationSource>2</InformationSource><Artifacts/><Spells/></Character><Character ID="nick "><Name>Nick Cave</Name><Location>1219</Location><Nation>22</Nation><Command>36</Command><TotalCommand>36</TotalCommand><Agent>0</Agent><TotalAgent>0</TotalAgent><Emmisary>90</Emmisary><TotalEmmisary>90</TotalEmmisary><Mage>0</Mage><TotalMage>0</TotalMage><Stealth>0</Stealth><TotalStealth>0</TotalStealth><Challenge>54</Challenge><Health>100</Health><Title></Title><InformationSource>0</InformationSource><Artifacts/><Spells/></Character><Character ID="lady "><Name>Lady Gaga</Name><Location>2123</Location><Nation>22</Nation><Command>10</Command><TotalCommand>10</TotalCommand><Agent>0</Agent><TotalAgent>0</TotalAgent><Emmisary>83</Emmisary><TotalEmmisary>83</TotalEmmisary><Mage>0</Mage><TotalMage>0</TotalMage><Stealth>0</Stealth><TotalStealth>0</TotalStealth><Challenge>43</Challenge><Health>100</Health><Title></Title><InformationSource>0</InformationSource><Artifacts/><Spells/></Character><Character ID="billy"><Name>Billy Corgan</Name><Location>2309</Location><Nation>22</Nation><Command>19</Command><TotalCommand>19</TotalCommand><Agent>0</Agent><TotalAgent>0</TotalAgent><Emmisary>68</Emmisary><TotalEmmisary>68</TotalEmmisary><Mage>0</Mage><TotalMage>0</TotalMage><Stealth>10</Stealth><TotalStealth>10</TotalStealth><Challenge>38</Challenge><Health>100</Health><Title></Title><InformationSource>0</InformationSource><Artifacts/><Spells/></Character><Character ID="huyna"><Name>Huyna</Name><Location>2309</Location><Nation>22</Nation><Command>0</Command><TotalCommand>0</TotalCommand><Agent>89</Agent><TotalAgent>89</TotalAgent><Emmisary>0</Emmisary><TotalEmmisary>0</TotalEmmisary><Mage>0</Mage><TotalMage>0</TotalMage><Stealth>0</Stealth><TotalStealth>0</TotalStealth><Challenge>66</Challenge><Health>100</Health><Title></Title><InformationSource>0</InformationSource><Artifacts/><Spells/></Character><Character ID="de gr"><Name>De Gregori</Name><Location>2423</Location><Nation>22</Nation><Command>0</Command><TotalCommand>0</TotalCommand><Agent>50</Agent><TotalAgent>50</TotalAgent><Emmisary>0</Emmisary><TotalEmmisary>0</TotalEmmisary><Mage>0</Mage><TotalMage>0</TotalMage><Stealth>0</Stealth><TotalStealth>0</TotalStealth><Challenge>37</Challenge><Health>100</Health><Title></Title><InformationSource>0</InformationSource><Artifacts/><Spells/></Character><Character ID="kesha"><Name>Kesha</Name><Location>2611</Location><Nation>22</Nation><Command>0</Command><TotalCommand>0</TotalCommand><Agent>81</Agent><TotalAgent>116</TotalAgent><Emmisary>0</Emmisary><TotalEmmisary>0</TotalEmmisary><Mage>0</Mage><TotalMage>0</TotalMage><Stealth>26</Stealth><TotalStealth>26</TotalStealth><Challenge>102</Challenge><Health>65</Health><Title></Title><InformationSource>0</InformationSource><Artifacts><Artifact>#11 Maikarama</Artifact><Artifact>#58 Vasamacil</Artifact><Artifact>#176 Ring of Wind</Artifact></Artifacts><Spells/></Character><Character ID="marhw"><Name>Marhwini</Name><Location>3706</Location><Nation>22</Nation><Command>0</Command><TotalCommand>0</TotalCommand><Agent>40</Agent><TotalAgent>40</TotalAgent><Emmisary>0</Emmisary><TotalEmmisary>0</TotalEmmisary><Mage>0</Mage><TotalMage>0</TotalMage><Stealth>0</Stealth><TotalStealth>0</TotalStealth><Challenge>30</Challenge><Health>100</Health><Title></Title><InformationSource>0</InformationSource><Artifacts/><Spells/></Character><Character ID="brego"><Name>Bregolas</Name><Location>3708</Location><Nation>22</Nation><Command>10</Command><TotalCommand>10</TotalCommand><Agent>30</Agent><TotalAgent>30</TotalAgent><Emmisary>0</Emmisary><TotalEmmisary>0</TotalEmmisary><Mage>0</Mage><TotalMage>0</TotalMage><Stealth>30</Stealth><TotalStealth>30</TotalStealth><Challenge>24</Challenge><Health>100</Health><Title></Title><InformationSource>0</InformationSource><Artifacts/><Spells/></Character><Character ID="lynyr"><Name>Lynyrd Skynyrd</Name><Location>3713</Location><Nation>22</Nation><Command>0</Command><TotalCommand>0</TotalCommand><Agent>52</Agent><TotalAgent>52</TotalAgent><Emmisary>0</Emmisary><TotalEmmisary>0</TotalEmmisary><Mage>0</Mage><TotalMage>0</TotalMage><Stealth>0</Stealth><TotalStealth>0</TotalStealth><Challenge>39</Challenge><Health>100</Health><Title></Title><InformationSource>0</InformationSource><Artifacts/><Spells/></Character><Character ID="john "><Name>John Miles</Name><Location>4015</Location><Nation>22</Nation><Command>64</Command><TotalCommand>64</TotalCommand><Agent>0</Agent><TotalAgent>0</TotalAgent><Emmisary>59</Emmisary><TotalEmmisary>59</TotalEmmisary><Mage>0</Mage><TotalMage>0</TotalMage><Stealth>0</Stealth><TotalStealth>0</TotalStealth><Challenge>71</Challenge><Health>100</Health><Title></Title><InformationSource>0</InformationSource><Artifacts/><Spells/></Character><Character ID="beyon"><Name>Beyonce Knowles</Name><Location>4112</Location><Nation>22</Nation><Command>44</Command><TotalCommand>44</TotalCommand><Agent>53</Agent><TotalAgent>53</TotalAgent><Emmisary>0</Emmisary><TotalEmmisary>0</TotalEmmisary><Mage>55</Mage><TotalMage>55</TotalMage><Stealth>0</Stealth><TotalStealth>0</TotalStealth><Challenge>75</Challenge><Health>100</Health><Title></Title><InformationSource>0</InformationSource><Artifacts/><Spells><Spell>#102 Barriers(64)</Spell><Spell>#404 Perceive Relations(69)</Spell><Spell>#412 Research Artifact(85)</Spell><Spell>#414 Scry Hex(87)</Spell><Spell>#415 Scry Area(94)</Spell><Spell>#418 Locate Artifact(80)</Spell><Spell>#510 Conjure Food(84)</Spell></Spells></Character><Character ID="ludov"><Name>Ludovico Einaudi</Name><Location>4112</Location><Nation>22</Nation><Command>70</Command><TotalCommand>70</TotalCommand><Agent>0</Agent><TotalAgent>0</TotalAgent><Emmisary>0</Emmisary><TotalEmmisary>0</TotalEmmisary><Mage>65</Mage><TotalMage>65</TotalMage><Stealth>0</Stealth><TotalStealth>0</TotalStealth><Challenge>106</Challenge><Health>100</Health><Title></Title><InformationSource>0</InformationSource><Artifacts><Artifact>#92 Skull Flail</Artifact></Artifacts><Spells><Spell>#102 Barriers(95)</Spell><Spell>#106 Deflections(78)</Spell><Spell>#412 Research Artifact(82)</Spell><Spell>#418 Locate Artifact(93)</Spell><Spell>#510 Conjure Food(74)</Spell></Spells></Character><Character ID="fredd"><Name>Freddie Mercury</Name><Location>4233</Location><Nation>22</Nation><Command>0</Command><TotalCommand>0</TotalCommand><Agent>92</Agent><TotalAgent>92</TotalAgent><Emmisary>0</Emmisary><TotalEmmisary>0</TotalEmmisary><Mage>0</Mage><TotalMage>0</TotalMage><Stealth>30</Stealth><TotalStealth>30</TotalStealth><Challenge>69</Challenge><Health>100</Health><Title></Title><InformationSource>0</InformationSource><Artifacts><Artifact>#163 Voice of the Dark Tower</Artifact></Artifacts><Spells/></Character><Character ID="vasco"><Name>Vasco</Name><Location>4233</Location><Nation>22</Nation><Command>0</Command><TotalCommand>0</TotalCommand><Agent>80</Agent><TotalAgent>90</TotalAgent><Emmisary>0</Emmisary><TotalEmmisary>0</TotalEmmisary><Mage>0</Mage><TotalMage>0</TotalMage><Stealth>24</Stealth><TotalStealth>24</TotalStealth><Challenge>67</Challenge><Health>100</Health><Title></Title><InformationSource>0</InformationSource><Artifacts><Artifact>#53 Listening Helm</Artifact></Artifacts><Spells/></Character><Character ID="dolce"><Name>Dolce Nera</Name><Location>4332</Location><Nation>22</Nation><Command>0</Command><TotalCommand>0</TotalCommand><Agent>65</Agent><TotalAgent>65</TotalAgent><Emmisary>0</Emmisary><TotalEmmisary>0</TotalEmmisary><Mage>0</Mage><TotalMage>0</TotalMage><Stealth>0</Stealth><TotalStealth>0</TotalStealth><Challenge>48</Challenge><Health>75</Health><Title></Title><InformationSource>0</InformationSource><Artifacts/><Spells/></Character><Character ID="elio "><Name>Elio</Name><Location>4334</Location><Nation>22</Nation><Command>0</Command><TotalCommand>0</TotalCommand><Agent>57</Agent><TotalAgent>57</TotalAgent><Emmisary>0</Emmisary><TotalEmmisary>0</TotalEmmisary><Mage>0</Mage><TotalMage>0</TotalMage><Stealth>0</Stealth><TotalStealth>0</TotalStealth><Challenge>42</Challenge><Health>100</Health><Title></Title><InformationSource>0</InformationSource><Artifacts/><Spells/></Character><Character ID="gotye"><Name>Gotye</Name><Location>4426</Location><Nation>22</Nation><Command>0</Command><TotalCommand>0</TotalCommand><Agent>61</Agent><TotalAgent>61</TotalAgent><Emmisary>0</Emmisary><TotalEmmisary>0</TotalEmmisary><Mage>0</Mage><TotalMage>0</TotalMage><Stealth>0</Stealth><TotalStealth>0</TotalStealth><Challenge>45</Challenge><Health>89</Health><Title></Title><InformationSource>0</InformationSource><Artifacts/><Spells/></Character><Character ID="micha"><Name>Michael Buble</Name><Location>4426</Location><Nation>22</Nation><Command>54</Command><TotalCommand>54</TotalCommand><Agent>0</Agent><TotalAgent>0</TotalAgent><Emmisary>0</Emmisary><TotalEmmisary>0</TotalEmmisary><Mage>61</Mage><TotalMage>61</TotalMage><Stealth>0</Stealth><TotalStealth>0</TotalStealth><Challenge>74</Challenge><Health>100</Health><Title></Title><InformationSource>0</InformationSource><Artifacts/><Spells><Spell>#2 Minor Heal(99)</Spell><Spell>#102 Barriers(60)</Spell><Spell>#106 Deflections(83)</Spell><Spell>#112 Shields(65)</Spell><Spell>#413 Scry Population Center(79)</Spell><Spell>#415 Scry Area(77)</Spell><Spell>#416 Reveal Production(82)</Spell><Spell>#510 Conjure Food(100)</Spell></Spells></Character><Character ID="tarja"><Name>Tarja Turunen</Name><Location>4426</Location><Nation>22</Nation><Command>0</Command><TotalCommand>0</TotalCommand><Agent>77</Agent><TotalAgent>77</TotalAgent><Emmisary>0</Emmisary><TotalEmmisary>0</TotalEmmisary><Mage>0</Mage><TotalMage>0</TotalMage><Stealth>0</Stealth><TotalStealth>0</TotalStealth><Challenge>57</Challenge><Health>100</Health><Title></Title><InformationSource>0</InformationSource><Artifacts/><Spells/></Character></Characters>
<Economy><Nation><ArmyMaint>15550</ArmyMaint><PopMaint>6000</PopMaint><CharMaint>32300</CharMaint><TotalMaint>53850</TotalMaint><TaxRate>60</TaxRate><Revenue>41790</Revenue><Surplus>-12060</Surplus><Reserve>2579</Reserve><TaxBase>23</TaxBase></Nation><Market><Product type="le"><BuyPrice>2</BuyPrice><SellPrice>1</SellPrice><MarketAvail>27467</MarketAvail><NationStores>3070</NationStores><NationProduction>945</NationProduction></Product><Product type="br"><BuyPrice>2</BuyPrice><SellPrice>1</SellPrice><MarketAvail>35010</MarketAvail><NationStores>2337</NationStores><NationProduction>380</NationProduction></Product><Product type="st"><BuyPrice>3</BuyPrice><SellPrice>2</SellPrice><MarketAvail>14911</MarketAvail><NationStores>2893</NationStores><NationProduction>400</NationProduction></Product><Product type="mi"><BuyPrice>13</BuyPrice><SellPrice>8</SellPrice><MarketAvail>3356</MarketAvail><NationStores>87</NationStores><NationProduction>70</NationProduction></Product><Product type="fo"><BuyPrice>2</BuyPrice><SellPrice>1</SellPrice><MarketAvail>292234</MarketAvail><NationStores>374</NationStores><NationProduction>4270</NationProduction></Product><Product type="ti"><BuyPrice>2</BuyPrice><SellPrice>1</SellPrice><MarketAvail>24179</MarketAvail><NationStores>1976</NationStores><NationProduction>988</NationProduction></Product><Product type="mo"><BuyPrice>7</BuyPrice><SellPrice>4</SellPrice><MarketAvail>4131</MarketAvail><NationStores>1928</NationStores><NationProduction>88</NationProduction></Product></Market></Economy>
<PopCentres><PopCentre HexID="1219"><Name>Dannedhir</Name><Nation>22</Nation><NationAllegience>0</NationAllegience><FortificationLevel>0</FortificationLevel><Size>2</Size><Dock>0</Dock><Capital>0</Capital><Loyalty>54</Loyalty><InformationSource>1</InformationSource><Hidden>0</Hidden></PopCentre><PopCentre HexID="2123"><Name>Barad Carchoth</Name><Nation>17</Nation><NationAllegience>0</NationAllegience><FortificationLevel>0</FortificationLevel><Size>2</Size><Dock>0</Dock><Capital>0</Capital><Loyalty>0</Loyalty><InformationSource>3</InformationSource><Hidden>0</Hidden></PopCentre><PopCentre HexID="2219"><Name>Lookout</Name><Nation>22</Nation><NationAllegience>0</NationAllegience><FortificationLevel>0</FortificationLevel><Size>1</Size><Dock>0</Dock><Capital>0</Capital><Loyalty>41</Loyalty><InformationSource>1</InformationSource><Hidden>0</Hidden></PopCentre><PopCentre HexID="2309"><Name>Cameth Brin</Name><Nation>15</Nation><NationAllegience>0</NationAllegience><FortificationLevel>2</FortificationLevel><Size>2</Size><Dock>0</Dock><Capital>0</Capital><Loyalty>0</Loyalty><InformationSource>3</InformationSource><Hidden>0</Hidden></PopCentre><PopCentre HexID="2423"><Name>Jakhirai</Name><Nation>13</Nation><NationAllegience>0</NationAllegience><FortificationLevel>0</FortificationLevel><Size>2</Size><Dock>0</Dock><Capital>0</Capital><Loyalty>0</Loyalty><InformationSource>3</InformationSource><Hidden>0</Hidden></PopCentre><PopCentre HexID="2510"><Name></Name><Nation>0</Nation><NationAllegience>0</NationAllegience><FortificationLevel>0</FortificationLevel><Size>6</Size><Dock>0</Dock><Capital>0</Capital><Loyalty>0</Loyalty><InformationSource>2</InformationSource><Hidden>0</Hidden></PopCentre><PopCentre HexID="3321"><Name>Ampano</Name><Nation>22</Nation><NationAllegience>0</NationAllegience><FortificationLevel>0</FortificationLevel><Size>1</Size><Dock>0</Dock><Capital>0</Capital><Loyalty>37</Loyalty><InformationSource>1</InformationSource><Hidden>0</Hidden></PopCentre><PopCentre HexID="3326"><Name>Bad Romance</Name><Nation>22</Nation><NationAllegience>0</NationAllegience><FortificationLevel>0</FortificationLevel><Size>1</Size><Dock>0</Dock><Capital>0</Capital><Loyalty>20</Loyalty><InformationSource>1</InformationSource><Hidden>0</Hidden></PopCentre><PopCentre HexID="3422"><Name>Lolituma</Name><Nation>22</Nation><NationAllegience>0</NationAllegience><FortificationLevel>0</FortificationLevel><Size>1</Size><Dock>0</Dock><Capital>0</Capital><Loyalty>36</Loyalty><InformationSource>1</InformationSource><Hidden>0</Hidden></PopCentre><PopCentre HexID="3607"><Name>Unknown (Map Icon)</Name><Nation>0</Nation><NationAllegience>0</NationAllegience><FortificationLevel>0</FortificationLevel><Size>2</Size><Dock>0</Dock><Capital>0</Capital><Loyalty>0</Loyalty><InformationSource>4</InformationSource><Hidden>0</Hidden></PopCentre><PopCentre HexID="3612"><Name>Unknown (Map Icon)</Name><Nation>0</Nation><NationAllegience>0</NationAllegience><FortificationLevel>1</FortificationLevel><Size>3</Size><Dock>1</Dock><Capital>0</Capital><Loyalty>0</Loyalty><InformationSource>4</InformationSource><Hidden>0</Hidden></PopCentre><PopCentre HexID="3706"><Name>Lagna Sa</Name><Nation>23</Nation><NationAllegience>0</NationAllegience><FortificationLevel>1</FortificationLevel><Size>4</Size><Dock>0</Dock><Capital>0</Capital><Loyalty>0</Loyalty><InformationSource>3</InformationSource><Hidden>0</Hidden></PopCentre><PopCentre HexID="3707"><Name>Trannel</Name><Nation>22</Nation><NationAllegience>0</NationAllegience><FortificationLevel>0</FortificationLevel><Size>3</Size><Dock>0</Dock><Capital>0</Capital><Loyalty>44</Loyalty><InformationSource>1</InformationSource><Hidden>0</Hidden></PopCentre><PopCentre HexID="3708"><Name>Thiach</Name><Nation>23</Nation><NationAllegience>0</NationAllegience><FortificationLevel>0</FortificationLevel><Size>2</Size><Dock>0</Dock><Capital>0</Capital><Loyalty>0</Loyalty><InformationSource>3</InformationSource><Hidden>0</Hidden></PopCentre><PopCentre HexID="3711"><Name>Unknown (Map Icon)</Name><Nation>0</Nation><NationAllegience>0</NationAllegience><FortificationLevel>1</FortificationLevel><Size>3</Size><Dock>0</Dock><Capital>0</Capital><Loyalty>0</Loyalty><InformationSource>4</InformationSource><Hidden>0</Hidden></PopCentre><PopCentre HexID="3712"><Name>Unknown (Map Icon)</Name><Nation>0</Nation><NationAllegience>0</NationAllegience><FortificationLevel>1</FortificationLevel><Size>5</Size><Dock>2</Dock><Capital>0</Capital><Loyalty>0</Loyalty><InformationSource>4</InformationSource><Hidden>0</Hidden></PopCentre><PopCentre HexID="3713"><Name>Campo</Name><Nation>14</Nation><NationAllegience>0</NationAllegience><FortificationLevel>0</FortificationLevel><Size>2</Size><Dock>0</Dock><Capital>0</Capital><Loyalty>0</Loyalty><InformationSource>3</InformationSource><Hidden>0</Hidden></PopCentre><PopCentre HexID="3716"><Name>Unknown (Map Icon)</Name><Nation>0</Nation><NationAllegience>0</NationAllegience><FortificationLevel>0</FortificationLevel><Size>2</Size><Dock>0</Dock><Capital>0</Capital><Loyalty>0</Loyalty><InformationSource>4</InformationSource><Hidden>0</Hidden></PopCentre><PopCentre HexID="3718"><Name>Unknown (Map Icon)</Name><Nation>0</Nation><NationAllegience>0</NationAllegience><FortificationLevel>0</FortificationLevel><Size>2</Size><Dock>0</Dock><Capital>0</Capital><Loyalty>0</Loyalty><InformationSource>4</InformationSource><Hidden>0</Hidden></PopCentre><PopCentre HexID="3721"><Name></Name><Nation>19</Nation><NationAllegience>0</NationAllegience><FortificationLevel>0</FortificationLevel><Size>1</Size><Dock>0</Dock><Capital>0</Capital><Loyalty>0</Loyalty><InformationSource>2</InformationSource><Hidden>0</Hidden></PopCentre><PopCentre HexID="3807"><Name>Unknown (Map Icon)</Name><Nation>0</Nation><NationAllegience>0</NationAllegience><FortificationLevel>1</FortificationLevel><Size>4</Size><Dock>0</Dock><Capital>0</Capital><Loyalty>0</Loyalty><InformationSource>4</InformationSource><Hidden>0</Hidden></PopCentre><PopCentre HexID="3811"><Name>Unknown (Map Icon)</Name><Nation>0</Nation><NationAllegience>0</NationAllegience><FortificationLevel>1</FortificationLevel><Size>3</Size><Dock>0</Dock><Capital>0</Capital><Loyalty>0</Loyalty><InformationSource>4</InformationSource><Hidden>0</Hidden></PopCentre><PopCentre HexID="3912"><Name>Unknown (Map Icon)</Name><Nation>0</Nation><NationAllegience>0</NationAllegience><FortificationLevel>1</FortificationLevel><Size>4</Size><Dock>0</Dock><Capital>0</Capital><Loyalty>0</Loyalty><InformationSource>4</InformationSource><Hidden>0</Hidden></PopCentre><PopCentre HexID="3921"><Name></Name><Nation>0</Nation><NationAllegience>0</NationAllegience><FortificationLevel>0</FortificationLevel><Size>6</Size><Dock>0</Dock><Capital>0</Capital><Loyalty>0</Loyalty><InformationSource>2</InformationSource><Hidden>0</Hidden></PopCentre><PopCentre HexID="4012"><Name>Unknown (Map Icon)</Name><Nation>0</Nation><NationAllegience>0</NationAllegience><FortificationLevel>1</FortificationLevel><Size>2</Size><Dock>0</Dock><Capital>0</Capital><Loyalty>0</Loyalty><InformationSource>4</InformationSource><Hidden>0</Hidden></PopCentre><PopCentre HexID="4013"><Name>Unknown (Map Icon)</Name><Nation>0</Nation><NationAllegience>0</NationAllegience><FortificationLevel>2</FortificationLevel><Size>4</Size><Dock>0</Dock><Capital>0</Capital><Loyalty>0</Loyalty><InformationSource>4</InformationSource><Hidden>0</Hidden></PopCentre><PopCentre HexID="4015"><Name>Radio Gaga</Name><Nation>22</Nation><NationAllegience>0</NationAllegience><FortificationLevel>1</FortificationLevel><Size>4</Size><Dock>0</Dock><Capital>0</Capital><Loyalty>62</Loyalty><InformationSource>1</InformationSource><Hidden>0</Hidden></PopCentre><PopCentre HexID="4017"><Name>Ghost love score</Name><Nation>22</Nation><NationAllegience>0</NationAllegience><FortificationLevel>0</FortificationLevel><Size>1</Size><Dock>0</Dock><Capital>0</Capital><Loyalty>19</Loyalty><InformationSource>1</InformationSource><Hidden>0</Hidden></PopCentre><PopCentre HexID="4111"><Name>The Knife</Name><Nation>22</Nation><NationAllegience>0</NationAllegience><FortificationLevel>1</FortificationLevel><Size>2</Size><Dock>0</Dock><Capital>0</Capital><Loyalty>33</Loyalty><InformationSource>1</InformationSource><Hidden>0</Hidden></PopCentre><PopCentre HexID="4112"><Name>Innuendo</Name><Nation>22</Nation><NationAllegience>0</NationAllegience><FortificationLevel>2</FortificationLevel><Size>5</Size><Dock>2</Dock><Capital>1</Capital><Loyalty>84</Loyalty><InformationSource>1</InformationSource><Hidden>0</Hidden></PopCentre><PopCentre HexID="4211"><Name>Nefeli</Name><Nation>22</Nation><NationAllegience>0</NationAllegience><FortificationLevel>1</FortificationLevel><Size>4</Size><Dock>0</Dock><Capital>0</Capital><Loyalty>57</Loyalty><InformationSource>1</InformationSource><Hidden>0</Hidden></PopCentre><PopCentre HexID="4212"><Name>Crystal Ball</Name><Nation>22</Nation><NationAllegience>0</NationAllegience><FortificationLevel>0</FortificationLevel><Size>2</Size><Dock>0</Dock><Capital>0</Capital><Loyalty>33</Loyalty><InformationSource>1</InformationSource><Hidden>0</Hidden></PopCentre><PopCentre HexID="4215"><Name>Unknown (Map Icon)</Name><Nation>0</Nation><NationAllegience>0</NationAllegience><FortificationLevel>0</FortificationLevel><Size>2</Size><Dock>0</Dock><Capital>0</Capital><Loyalty>0</Loyalty><InformationSource>4</InformationSource><Hidden>0</Hidden></PopCentre><PopCentre HexID="4233"><Name>The Aerie</Name><Nation>14</Nation><NationAllegience>0</NationAllegience><FortificationLevel>1</FortificationLevel><Size>4</Size><Dock>0</Dock><Capital>0</Capital><Loyalty>0</Loyalty><InformationSource>3</InformationSource><Hidden>0</Hidden></PopCentre><PopCentre HexID="4311"><Name>Breakthru</Name><Nation>22</Nation><NationAllegience>0</NationAllegience><FortificationLevel>1</FortificationLevel><Size>3</Size><Dock>0</Dock><Capital>0</Capital><Loyalty>51</Loyalty><InformationSource>1</InformationSource><Hidden>0</Hidden></PopCentre><PopCentre HexID="4332"><Name>Tal Sh'iar</Name><Nation>16</Nation><NationAllegience>0</NationAllegience><FortificationLevel>1</FortificationLevel><Size>3</Size><Dock>0</Dock><Capital>0</Capital><Loyalty>0</Loyalty><InformationSource>3</InformationSource><Hidden>0</Hidden></PopCentre><PopCentre HexID="4334"><Name>M'Kraan</Name><Nation>16</Nation><NationAllegience>0</NationAllegience><FortificationLevel>1</FortificationLevel><Size>2</Size><Dock>0</Dock><Capital>0</Capital><Loyalty>0</Loyalty><InformationSource>3</InformationSource><Hidden>0</Hidden></PopCentre><PopCentre HexID="4411"><Name>Forgotten Sons</Name><Nation>22</Nation><NationAllegience>0</NationAllegience><FortificationLevel>1</FortificationLevel><Size>3</Size><Dock>0</Dock><Capital>0</Capital><Loyalty>45</Loyalty><InformationSource>1</InformationSource><Hidden>0</Hidden></PopCentre><PopCentre HexID="4412"><Name>Telephone</Name><Nation>22</Nation><NationAllegience>0</NationAllegience><FortificationLevel>0</FortificationLevel><Size>2</Size><Dock>0</Dock><Capital>0</Capital><Loyalty>49</Loyalty><InformationSource>1</InformationSource><Hidden>0</Hidden></PopCentre><PopCentre HexID="4413"><Name>Mirror Mirror</Name><Nation>22</Nation><NationAllegience>0</NationAllegience><FortificationLevel>1</FortificationLevel><Size>2</Size><Dock>0</Dock><Capital>0</Capital><Loyalty>42</Loyalty><InformationSource>1</InformationSource><Hidden>0</Hidden></PopCentre><PopCentre HexID="4422"><Name>Purgatory</Name><Nation>22</Nation><NationAllegience>0</NationAllegience><FortificationLevel>3</FortificationLevel><Size>3</Size><Dock>0</Dock><Capital>0</Capital><Loyalty>59</Loyalty><InformationSource>1</InformationSource><Hidden>0</Hidden></PopCentre><PopCentre HexID="4426"><Name>Structure</Name><Nation>19</Nation><NationAllegience>0</NationAllegience><FortificationLevel>1</FortificationLevel><Size>3</Size><Dock>0</Dock><Capital>0</Capital><Loyalty>0</Loyalty><InformationSource>3</InformationSource><Hidden>0</Hidden></PopCentre></PopCentres><Armies><Army HexID="4015"><Nation>22</Nation><NationAllegience>0</NationAllegience><Size>3</Size><TroopCount>1156</TroopCount><Commander>John Miles</Commander><CommanderTitle>Regent</CommanderTitle><ExtraInfo>1156HC</ExtraInfo><Navy>0</Navy><InformationSource>1</InformationSource><CharsTravellingWith></CharsTravellingWith></Army><Army HexID="4015"><Nation>0</Nation><NationAllegience>1</NationAllegience><Size>0</Size><TroopCount>0</TroopCount><Commander>Unknown (Map Icon)</Commander><CommanderTitle></CommanderTitle><ExtraInfo></ExtraInfo><Navy>0</Navy><InformationSource>4</InformationSource><CharsTravellingWith></CharsTravellingWith></Army><Army HexID="4017"><Nation>19</Nation><NationAllegience>0</NationAllegience><Size>2</Size><TroopCount>0</TroopCount><Commander>Orellana</Commander><CommanderTitle>Commander</CommanderTitle><ExtraInfo></ExtraInfo><Navy>0</Navy><InformationSource>3</InformationSource><CharsTravellingWith></CharsTravellingWith></Army><Army HexID="4017"><Nation>0</Nation><NationAllegience>2</NationAllegience><Size>0</Size><TroopCount>0</TroopCount><Commander>Unknown (Map Icon)</Commander><CommanderTitle></CommanderTitle><ExtraInfo></ExtraInfo><Navy>0</Navy><InformationSource>4</InformationSource><CharsTravellingWith></CharsTravellingWith></Army><Army HexID="4426"><Nation>22</Nation><NationAllegience>0</NationAllegience><Size>0</Size><TroopCount>1369</TroopCount><Commander>Michael Buble</Commander><CommanderTitle>Lord</CommanderTitle><ExtraInfo>1369HC</ExtraInfo><Navy>0</Navy><InformationSource>1</InformationSource><CharsTravellingWith>Gotye - Tarja Turunen</CharsTravellingWith></Army></Armies><NationInfo><EmptyPopHexes HexIDList="3608,3609,3610,3611,3613,3614,3615,3616,3617,3618,3619,3709,3710,3714,3715,3717,3719,3808,3809,3810,3812,3813,3814,3815,3816,3817,3818,3819,3907,3908,3909,3910,3911,3913,3914,3915,3916,3917,3918,3919,4007,4008,4009,4010,4011,4014,4016,4018,4019,4107,4108,4109,4110,4113,4114,4115,4116,4117,4118,4119,4207,4208,4209,4210,4213,4214,4216,4217,4218,4219,4307,4308,4309,4310,4312,4313,4314,4315,4316,4317,4318,4319,4407,4409,4415,4417,4419"/><PopHexes HexIDList="3607,3612,3707,3708,3711,3712,3713,3716,3718,3807,3811,3912,4012,4013,4015,4017,4111,4112,4211,4212,4215,4311,4411,4413"/><NationMessages><NationMessage>There are rumors of an armed conflict involving the Ground Pounders at 3121. </NationMessage><NationMessage>There are rumors of an armed conflict involving the Wise Council and the Tribes of Angmar at 1702. </NationMessage><NationMessage>There are rumors of the fall of a Strategic Site. </NationMessage><NationMessage>The loyalty was influenced/reduced at Dannedhir. </NationMessage><NationMessage>There are rumors of a sabotage attempt involving Oruthan at 3129. </NationMessage><NationMessage>1000 Mounts transported from the Once Upon a Time to Radio Gaga. </NationMessage><NationMessage>There are rumors of Gold being transported by caravan from Ar-Kuinder to Baltus. </NationMessage><NationMessage>Our populace reports that a season change is imminent! </NationMessage></NationMessages></NationInfo><Nations><Nation ID="0">Unknown</Nation><Nation ID="1">North Kingdom</Nation><Nation ID="2">South Kingdom</Nation><Nation ID="3">Wise Council</Nation><Nation ID="4">Acadians</Nation><Nation ID="5">Silent Assembly</Nation><Nation ID="6">Thorinar</Nation><Nation ID="7">Sapphic Enclave</Nation><Nation ID="8">Nameless</Nation><Nation ID="9">Ground Pounders</Nation><Nation ID="10">Sundered</Nation><Nation ID="11">Lohmai'gwaith</Nation><Nation ID="12">Sheri-Urk</Nation><Nation ID="13">Red Witches</Nation><Nation ID="14">Dark Feast</Nation><Nation ID="15">Twilight Hammer</Nation><Nation ID="16">Sh'iar Empire</Nation><Nation ID="17">Great Trollusk</Nation><Nation ID="18">Benîm an Pharazôn</Nation><Nation ID="19">RhunLandChattelCo</Nation><Nation ID="20">Tribes of Angmar</Nation><Nation ID="21">Lands</Nation><Nation ID="22">Sing a Song</Nation><Nation ID="23">Once Upon a Time</Nation><Nation ID="24">Plane</Nation><Nation ID="25">Alvernus</Nation></Nations></METurn>
